.gitignore
CHANGES.txt
CONTRIBUTORS.txt
MANIFEST.in
README.txt
setup.cfg
setup.py
bopen/__init__.py
bopen.atcontenttypes.egg-info/PKG-INFO
bopen.atcontenttypes.egg-info/SOURCES.txt
bopen.atcontenttypes.egg-info/dependency_links.txt
bopen.atcontenttypes.egg-info/entry_points.txt
bopen.atcontenttypes.egg-info/namespace_packages.txt
bopen.atcontenttypes.egg-info/not-zip-safe
bopen.atcontenttypes.egg-info/paster_plugins.txt
bopen.atcontenttypes.egg-info/requires.txt
bopen.atcontenttypes.egg-info/top_level.txt
bopen/atcontenttypes/README.txt
bopen/atcontenttypes/__init__.py
bopen/atcontenttypes/config.py
bopen/atcontenttypes/configure.zcml
bopen/atcontenttypes/skins.zcml
bopen/atcontenttypes/browser/__init__.py
bopen/atcontenttypes/browser/configure.zcml
bopen/atcontenttypes/browser/similarcontentportlet.pt
bopen/atcontenttypes/content/__init__.py
bopen/atcontenttypes/content/configure.zcml
bopen/atcontenttypes/content/richfolder.py
bopen/atcontenttypes/i18n/generated-en.po
bopen/atcontenttypes/i18n/generated-it.po
bopen/atcontenttypes/i18n/generated.pot
bopen/atcontenttypes/interfaces/__init__.py
bopen/atcontenttypes/interfaces/longdescription.py
bopen/atcontenttypes/interfaces/richfolder.py
bopen/atcontenttypes/portlets/__init__.py
bopen/atcontenttypes/portlets/configure.zcml
bopen/atcontenttypes/profiles/default/catalog.xml
bopen/atcontenttypes/profiles/default/factorytool.xml
bopen/atcontenttypes/profiles/default/metadata.xml
bopen/atcontenttypes/profiles/default/portlets.xml
bopen/atcontenttypes/profiles/default/rolemap.xml
bopen/atcontenttypes/profiles/default/skins.xml
bopen/atcontenttypes/profiles/default/types.xml
bopen/atcontenttypes/profiles/default/types/RichFolder.xml
bopen/atcontenttypes/profiles/default/types/RichPage.xml
bopen/atcontenttypes/skins/bopen_atcontenttypes_custom_templates/folder_summary_view.pt
bopen/atcontenttypes/tests/__init__.py
bopen/atcontenttypes/tests/base.py
bopen/atcontenttypes/tests/test_doctest.py
docs/HISTORY.txt
docs/INSTALL.txt
docs/LICENSE.GPL
docs/LICENSE.txt