Metadata-Version: 1.0
Name: bopen.atcontenttypes
Version: 0.1
Summary: B-Open AT Content Types for Plone
Home-page: http://www.bopen.eu/open-source/bopen.atcontenttypes
Author: B-Open Solutions srl
Author-email: UNKNOWN
License: GPL
Platform: UNKNOWN
Classifier: Framework :: Plone
Classifier: Intended Audience :: Developers
Classifier: License :: OSI Approved :: GNU General Public License (GPL)
